{
  "id": "tutorial-extras/dataengineering",
  "title": "Data Engineering with geol",
  "description": "Data Engineering with geol explains how to collect, normalize, and analyze product metadata (versions, release dates, end-of-life) for downstream analytics.",
  "source": "@site/docs/tutorial-extras/dataengineering.md",
  "sourceDirName": "tutorial-extras",
  "slug": "/tutorial-extras/dataengineering",
  "permalink": "/docs/tutorial-extras/dataengineering",
  "draft": false,
  "unlisted": false,
  "tags": [],
  "version": "current",
  "sidebarPosition": 2,
  "frontMatter": {
    "sidebar_position": 2
  },
  "sidebar": "tutorialSidebar",
  "previous": {
    "title": "asciidoc Toolchain",
    "permalink": "/docs/tutorial-extras/asciidoc-toolchain"
  }
}